mazemdp/__init__.py
mazemdp/_version.py
mazemdp/chrono.py
mazemdp/maze.py
mazemdp/maze_plotter.py
mazemdp/mdp.py
mazemdp/nbwidget.css
mazemdp/nbwidget.py
mazemdp/nbwidget.tsx
mazemdp/simple_action_space.py
mazemdp/toolbox.py
mazemdp-1.2.13.dist-info/licenses/LICENSE
mazemdp-1.2.13.dist-info/METADATA
mazemdp-1.2.13.dist-info/WHEEL
mazemdp-1.2.13.dist-info/top_level.txt
mazemdp-1.2.13.dist-info/RECORD
