Metadata-Version: 2.4
Name: mazemdp
Version: 1.2.13
Summary: An simple maze to test dynamic programming and tabular reinforcement learning algorithms
Author-email: Olivier Sigaud <Olivier.Sigaud@isir.upmc.fr>, Benjamin Piwowarski <benjamin.piwowarski@cnrs.fr>
Project-URL: homepage, https://github.com/osigaud/SimpleMazeMDP
License-File: LICENSE
Requires-Dist: numpy
Requires-Dist: matplotlib
Requires-Dist: ipyreact
Dynamic: license-file
